bas_web_map_inventory/__init__.py
bas_web_map_inventory/cli.py
bas_web_map_inventory/components/__init__.py
bas_web_map_inventory/components/airtable.py
bas_web_map_inventory/components/geoserver.py
bas_web_map_inventory/config.py
bas_web_map_inventory/resources/__init__.py
bas_web_map_inventory/resources/json_schemas/__init__.py
bas_web_map_inventory/resources/json_schemas/data-resources-schema.json
bas_web_map_inventory/resources/json_schemas/data-sources-schema.json
bas_web_map_inventory/resources/xml_schemas/__init__.py
bas_web_map_inventory/resources/xml_schemas/wms-1.3.0.xsd
bas_web_map_inventory/resources/xml_schemas/xlink.xsd
bas_web_map_inventory/resources/xml_schemas/xml.xsd
bas_web_map_inventory/utils.py
bas_web_map_inventory-0.4.0.dist-info/LICENSE.md
bas_web_map_inventory-0.4.0.dist-info/WHEEL
bas_web_map_inventory-0.4.0.dist-info/METADATA
bas_web_map_inventory-0.4.0.dist-info/RECORD
