Metadata-Version: 2.1
Name: bas-web-map-inventory
Version: 0.4.0
Summary: Inventory of geospatial layers and web maps provided by the BAS Mapping and Geographic Information Centre (MAGIC), visualised in Airtable.
Home-page: https://github.com/antarctica/web-map-inventory
Author: Felix Fennell
Author-email: felnne@bas.ac.uk
Requires-Python: >=3.8,<4.0
Classifier: Development Status :: 3 - Alpha
Classifier: Framework :: Flask
Classifier: Intended Audience :: Science/Research
Classifier: License :: Other/Proprietary License
Classifier: Programming Language :: Python :: 3
Classifier: Programming Language :: Python :: 3.8
Requires-Dist: Flask (>=1.1.1,<2.0.0)
Requires-Dist: OWSlib (>=0.19.0,<0.20.0)
Requires-Dist: airtable-python-wrapper (>=0.12.0,<0.13.0)
Requires-Dist: geoserver-restconfig (==1.0.2)
Requires-Dist: inquirer (>=2.6.3,<3.0.0)
Requires-Dist: jsonschema (>=3.2.0,<4.0.0)
Requires-Dist: lxml (==4.5.0)
Requires-Dist: pyproj (==2.6.0)
Requires-Dist: python-dotenv (>=0.10.3,<0.11.0)
Requires-Dist: sentry-sdk[flask] (>=0.13.5,<0.14.0)
Requires-Dist: str2bool (>=1.1,<2.0)
Requires-Dist: ulid-py (>=0.0.12,<0.0.13)
Project-URL: Repository, https://github.com/antarctica/web-map-inventory
